{
  "asin_from_details": "B00KHSCELS",
  "title": "Kaps Shoe Care Cream, Intensive Leather Care and Nourishing, Delicate, 70 colours",
  "current_price": 7.29,
  "original_price": 8.5,
  "main_image": "https://m.media-amazon.com/images/I/71pZ9HkfmiL._AC_SL1500_.jpg",
  "thumbnails": [
    "https://m.media-amazon.com/images/I/41cv0Mzo0zL._SL1500_.jpg",
    "https://m.media-amazon.com/images/I/417Wm3bOQiL._SL1500_.jpg",
    "https://m.media-amazon.com/images/I/31069-s03zL._SL1500_.jpg",
    "https://m.media-amazon.com/images/I/51Kps+ncwyL._SL1500_.jpg",
    "https://m.media-amazon.com/images/I/41nwzg9LPPL._SL1500_.jpg",
    "https://m.media-amazon.com/images/I/41uaYm3YXIL._SL1500_.jpg",
    "https://m.media-amazon.com/images/I/91c13nxO1YL._SL1500_PKmb-play-button-overlay-thumb_.jpg"
  ],
  "high_res_gallery": [],
  "amazon_product_details_section": {
    "Is discontinued by manufacturer\n                                    ‏\n                                    :\n                                    ‎": "No",
    "Package Dimensions\n                                    ‏\n                                    :\n                                    ‎": "10.9 x 8.7 x 5.4 cm; 100 g",
    "Date First Available\n                                    ‏\n                                    :\n                                    ‎": "25 April 2015",
    "Manufacturer\n                                    ‏\n                                    :\n                                    ‎": "Kaps",
    "ASIN\n                                    ‏\n                                    :\n                                    ‎": "B00KHSCELS",
    "Item model number\n                                    ‏\n                                    :\n                                    ‎": "03_0123_18",
    "Country of origin\n                                    ‏\n                                    :\n                                    ‎": "Poland",
    "Department\n                                    ‏\n                                    :\n                                    ‎": "Unisex",
    "Is discontinued by manufacturer\n                                    ‏": "‎ No",
    "Package Dimensions\n                                    ‏": "‎ 10.9 x 8.7 x 5.4 cm; 100 g",
    "Date First Available\n                                    ‏": "‎ 25 April 2015",
    "Manufacturer\n                                    ‏": "‎ Kaps",
    "ASIN\n                                    ‏": "‎ B00KHSCELS",
    "Item model number\n                                    ‏": "‎ 03_0123_18",
    "Country of origin\n                                    ‏": "‎ Poland",
    "Department\n                                    ‏": "‎ Unisex",
    "Best Sellers Rank": "703 in Fashion (See Top 100 in Fashion) 5 in Shoe Polishes",
    "Customer reviews": "4.5 4.5 out of 5 stars 2,099 ratings var dpAcrHasRegisteredArcLinkClickAction; P.when('A', 'ready').execute(function(A) { if (dpAcrHasRegisteredArcLinkClickAction !== true) { dpAcrHasRegisteredArcLinkClickAction = true; A.declarative( 'acrLink-click-metrics', 'click', { \"allowLinkDefault\": true }, function (event) { if (window.ue) { ue.count(\"acrLinkClickCount\", (ue.count(\"acrLinkClickCount\") || 0) + 1); } } ); } }); P.when('A', 'cf').execute(function(A) { A.declarative('acrStarsLink-click-metrics', 'click', { \"allowLinkDefault\" : true }, function(event){ if(window.ue) { ue.count(\"acrStarsLinkWithPopoverClickCount\", (ue.count(\"acrStarsLinkWithPopoverClickCount\") || 0) + 1); } }); });"
  },
  "dimensions_from_details": "‎ 10.9 x 8.7 x 5.4 cm; 100 g",
  "date_first_available_from_details": "‎ 25 April 2015",
  "manufacturer_from_details": "‎ Kaps",
  "prime_eligible": true,
  "fulfilled_by_amazon": false,
  "seller_info_text": "JMFA LTD",
  "sold_by_amazon": false,
  "rating": 4.5,
  "review_count": 2099,
  "availability_text": "In stock",
  "in_stock": true,
  "description": "Product Description Kaps Delicate Cream Lend an immediate buffed finish to your shoes As our shoes are part of our everyday life, it is important to clean them regularly to enjoy your shoes for many years to come. Kaps Delicate Cream is the perfect conditioner for genuine and faux leather shoes. suitable for faux and genuine leather cleans and nourishes and restores colour to revive from n