{
  "asin_from_details": "B000UO9BQ0",
  "title": "Pyrex Essentials Glass oval Roaster high resistance 26x18x6 cm",
  "current_price": 8.44,
  "original_price": 8.88,
  "main_image": "https://m.media-amazon.com/images/I/31HWs5CEsGL._AC_SL1200_.jpg",
  "thumbnails": [
    "https://m.media-amazon.com/images/I/2108IEEqeTL._SL1500_.jpg",
    "https://m.media-amazon.com/images/I/517D9a3WUaL._SL1500_.jpg",
    "https://m.media-amazon.com/images/I/31fWA94ZzHL._SL1500_.jpg",
    "https://m.media-amazon.com/images/I/31wy9DhG6+L._SL1500_.jpg",
    "https://m.media-amazon.com/images/I/213H99KccEL._SL1500_.jpg"
  ],
  "high_res_gallery": [],
  "amazon_product_details_section": {
    "ASIN": "B000UO9BQ0",
    "Date First Available": "27 July 2010"
  },
  "date_first_available_from_details": "27 July 2010",
  "prime_eligible": false,
  "fulfilled_by_amazon": false,
  "seller_info_text": "UK Direct 247",
  "sold_by_amazon": false,
  "rating": 4.5,
  "review_count": 1057,
  "availability_text": "In stock",
  "in_stock": true,
  "features": [
    "PIREX Oval tray Excellence 25x17 oking pot",
    "Borosilicate glass: ideal for cooking in the oven and storing in the refrigerator. Scratch resistant. Healthy and hygienic material that does not retain odors and does not stain.",
    "Scratch resistant",
    "Made in France."
  ],
  "description": "Product Description Pyrex, a committed French brand! At Pyrex, we are committed to a free and uninhibited style of cooking, free from codes of perfection. For over 100 years, our Pyrex cookware and storage containers have been inspired by a love of French cuisine. Our commitment is to develop and produce healthy and durable glass products in our French factory, suitable for a wide range of uses! Previous page A dish to suit every situation! Discover our wide range of Pyrex oven dishes to suit all your kitchens! Scratch resistant Can be cut directly inside the dish without damaging it Dishwasher safe Hygienic material that won't accumulate stains or odours Easy to wash Cook and reheat Oven and microwave safe Deep dish for easy cooking Easy to use Gigognables for optimised storage Withstands temperatures from -40°C to +300°C Serve on the table Next page 1 Discover our roasters 2 Scratch resistant 3 Easy to wash 4 Cook and reheat 5 Easy to use Discover our roasters ! 3 Glass Oven Dishes 8 pax Add To Basket 2 lasagnas glass dishes Add To Basket 4 Glass Oven Dishes 10 px Add To Basket 3 Glass Oven Dishes 6 pax Add To Basket Customer Reviews 4.7 out of 5 stars 5,328 4.8 out of 5 stars 878 4.9 out of 5 stars 46 4.8 out of 5 stars 217 Price £25.89 £ 25 . 89 £23.94 £ 23 . 94 £34.49 £ 34 . 49 £26.89 £ 26 . 89 Wide handles ✔ ✘ ✔ ✔ Deep dish ✔ ✔ ✔ ✔ Scratch resistance ✔ ✔ ✔ ✔ Airfryer safe ✔ ✔ ✔ ✔ Oven safe ✔ ✔ ✔ ✔ Microwave safe ✔ ✔ ✔ ✔ Dishwasher safe ✔ ✔ ✔ ✔ Freeze &amp; Fridge safe ✔ ✔ ✔ ✔ Reusable ✔ ✔ ✔ ✔ Pyrex Borosilicate glass ✔ ✔ ✔ ✔ Made in France ✔ ✔ ✔ ✔ Ideal for Family 4 - 6 pax &amp; friends Lasagnas fans Big family &amp; friends First equipment The video showcases the product in use. The video guides you through product setup. The video compares multiple products. The video shows the product being unpacked. Video Player is loading. Click to play video Play Mute Current Time&nbsp; 0:00 / Duration&nbsp; 0:00 Loaded : 0% Stream Type&nbsp; LIVE Seek to live, currently behind live LIVE Remaining Time&nbsp; - 0:00 &nbsp; 1x Playback Rate Chapters Chapters Descriptions descriptions off , selected Captions Captions off , selected Audio Track Fullscreen This is a modal window. A COMMITMENT MADE TO LAST Sustainable products We are committed to bringing the highest quality cookware to every home in the world. Preserving our environment Our aim is to continually reduce our CO2 emissions, improve waste management and minimise our footprint on the planet. French manufacturing Pyrex glass has been made in France since 1970, symbolising the excellence of the French glass industry thanks to unrivalled expertise. Stop food waste! At Pyrex, we fight food waste with the conviction that food that is better preserved and consumed is also food that is thrown away less. Previous page Next page",
  "specifications_table": {
    "Brand": "‎Pyrex",
    "Model Number": "‎222B000/5046",
    "Colour": "‎Mother-of-pearl",
    "Product Dimensions": "‎25 x 17 x 6 cm; 767 g",
    "Capacity": "‎1.3 litres",
    "Material": "‎Glass",
    "Special Features": "‎Dishwasher-Safe, Microwave safe",
    "Item Weight": "‎767 g"
  },
  "selleramp": {
    "status": "SellerAmp extraction disabled"
  },
  "keepa": {
    "status": "Extraction process completed",
    "sales_rank_details_table": {
      "main_cat_current_rank": 113304,
      "main_cat_name": "Home & Kitchen 12 drops / month",
      "sub_cat_current_rank": 27,
      "sub_cat_name": "Lasagna Dishes 4"
    },
    "ai_graph_analysis_status": "Keepa Graph AI Analysis disabled",
    "product_details_tab_data": {
      "Title": "Pyrex Essentials Glass oval Roaster high resistance 26x18x6 cm",
      "Sales Rank - Reference": "Home & Kitchen",
      "Sales Rank - Display Group": "kitchen_display_on_website",
      "Reviews - Rating": 4.5,
      "Reviews - Rating Count": 1.0,
      "Last Price Change": "just now",
      "Buy Box - Buy Box Seller": "UK Direct 247 (78% positive over last 12 months)",
      "Buy Box - Shipping Country": "GB",
      "Buy Box - Strikethrough Price": "£ 8.88",
      "FBA Pick&Pack Fee": 3.14,
      "Referral Fee %": "15.05 %",
      "Referral Fee based on current Buy Box price": 1.27,
      "Lowest FBM Seller": "UK Direct 247 (78% positive over last 12 months)",
      "Total Offer Count": "7",
      "Tracking since": "2011/05/21",
      "Listed since": "2010/07/27",
      "Categories - Root": "Home & Kitchen",
      "Categories - Sub": "Lasagna Dishes / Home & Garden",
      "Categories - Tree": "Home & Kitchen › Cooking & Dining › Cookware › Baking Dishes › Lasagna Dishes",
      "Website Display Group - Name": "Kitchen",
      "ASIN": "B000UO9BQ0",
      "Product Codes - EAN": "5055942986412, 5054480144230, 5057065087014, 3137610001282",
      "Product Codes - GTIN": "03137610001282",
      "Product Codes - PartNumber": "222B000/5046",
      "Parent ASIN": "B01207WQWK",
      "Variation ASINs": "B000UOCXTW, B000UO9BQ0, B000UO9BR4",
      "Freq. Bought Together": "B000WFFZ94, B001TNTNQE",
      "Type": "CASSEROLES",
      "Manufacturer": "Pyrex",
      "Brand": "Pyrex",
      "Brand Store Name": "Pyrex",
      "Brand Store URL Name": "Pyrex®",
      "Brand Store URL": "https://www.amazon.com/stores/Pyrex®/page/0648484F-6F7D-41CD-853C-6447960549EE",
      "Product Group": "Home",
      "Model": "222B000/5046",
      "Color": "Mother-of-pearl",
      "Size": "25 x 17 cm",
      "Unit Details - Unit Value": "0.5",
      "Unit Details - Unit Type": "gram",
      "Style": "Oval",
      "Material": "Glass",
      "Binding": "Home",
      "Number of Items": "1",
      "Release Date": "2011-03-24",
      "Package - Dimension (cm³)": "28.2 x 19.2 x 10.8 cm (= 5,848 cm³ )",
      "Package - Weight (g)": "780",
      "Package - Quantity": "1",
      "Item - Dimension (cm³)": "25.0 x 17.0 x 6.0 cm (= 2,550 cm³ )",
      "Item - Weight (g)": "767"
    }
  },
  "sales_rank": 113304,
  "category": "Home & Kitchen 12",
  "sales_rank_source": "Keepa_SalesRankDetailsTable",
  "estimated_monthly_sales_from_bsr": 5,
  "asin_extracted_from_page": "B000UO9BQ0",
  "asin_queried": "B000UO9BQ0",
  "asin": "B000UO9BQ0",
  "_search_method_used": "EAN"
}