{
  "asin_from_details": "B071XRT5JR",
  "title": "Boxed Children's Birthday Card (Pack of 8)",
  "current_price": 8.49,
  "original_price": 11.99,
  "main_image": "https://m.media-amazon.com/images/I/71YP1vM74bL._AC_SL1181_.jpg",
  "thumbnails": [
    "https://m.media-amazon.com/images/I/51u5DOjUe-L._SL1500_.jpg"
  ],
  "high_res_gallery": [],
  "amazon_product_details_section": {
    "ASIN": "B071XRT5JR",
    "Date First Available": "15 April 2017"
  },
  "date_first_available_from_details": "15 April 2017",
  "prime_eligible": false,
  "fulfilled_by_amazon": false,
  "rating": 4.0,
  "review_count": 16,
  "availability_text": "Temporarily out of stock.",
  "in_stock": false,
  "features": [
    "Model Number: 4490",
    "Item Package Quantity: 1",
    "Package Weight: 140 grams",
    "Package Dimensions (L x B x H) in cm: 3.05 x 14.73 x 15.49"
  ],
  "description": "Keepsake box of 8 Children's design greeting cards each 15cm square with simple \"Happy Birthday\" message printed inside.",
  "specifications_table": {
    "Brand": "‎Just to Say",
    "Model Number": "‎4490",
    "Product Dimensions": "‎15.1 x 3.2 x 15.1 cm; 132.9 g",
    "Pre-printed": "‎Happy Birthday",
    "Number of Items": "‎8",
    "Manufacturer Part Number": "‎4490",
    "Item Weight": "‎133 g"
  },
  "selleramp": {
    "status": "SellerAmp extraction disabled"
  },
  "keepa": {
    "status": "Extraction process completed",
    "ai_graph_analysis_status": "Keepa Graph AI Analysis disabled",
    "product_details_tab_data": {
      "Title": "Just to Say Boxed Children's Birthday Card (Pack of 8)",
      "Sales Rank - Reference": "Stationery & Office Supplies",
      "Reviews - Rating": 4.0,
      "Reviews - Rating Count": 16.0,
      "Last Price Change": "4 days ago",
      "Buy Box - Buy Box Seller": "N R Creations (91% positive over last 12 months)",
      "Buy Box - Shipping Country": "GB",
      "FBA Pick&Pack Fee": 2.42,
      "Referral Fee %": "15.15 %",
      "Referral Fee based on current Buy Box price": 0.45,
      "Lowest FBM Seller": "N R Creations (91% positive over last 12 months)",
      "Total Offer Count": "9",
      "Tracking since": "2018/01/01",
      "Listed since": "2017/04/15",
      "Categories - Root": "Everything Else",
      "Categories - Sub": "Categories",
      "Website Display Group - Name": "Office Product",
      "ASIN": "B071XRT5JR",
      "Product Codes - EAN": "5013922044903",
      "Product Codes - GTIN": "05013922044903",
      "Product Codes - PartNumber": "4490",
      "Type": "GREETING_CARD",
      "Brand": "Just to Say",
      "Product Group": "Office Product",
      "Model": "4490",
      "Pattern": "Letter Print",
      "Style": "Modern",
      "Specific Uses": "Birthday Card",
      "Binding": "Accessory",
      "Number of Items": "8",
      "Package - Dimension (cm³)": "15.5 x 14.7 x 3.0 cm (= 684 cm³ )",
      "Package - Weight (g)": "140",
      "Package - Quantity": "1",
      "Item - Dimension (cm³)": "15.1 x 3.2 x 15.1 cm (= 730 cm³ )",
      "Item - Weight (g)": "133"
    }
  },
  "eans_on_page": [
    "5013922044903"
  ],
  "ean_on_page_source": "Keepa_Product_Details",
  "ean_on_page": "5013922044903",
  "asin_extracted_from_page": "B071XRT5JR",
  "asin_queried": "B071XRT5JR",
  "asin": "B071XRT5JR",
  "_search_method_used": "EAN"
}