{
  "asin_from_details": "B09LR297CC",
  "title": "RSW Pack Of 6 Baby Sensory Balls Assorted Textures For Motor Skills & Development And Perfect Colour Teaching Learning",
  "current_price": 7.94,
  "original_price": 19.99,
  "main_image": "https://m.media-amazon.com/images/I/71NgBECO6JL._AC_SL1500_.jpg",
  "thumbnails": [
    "https://m.media-amazon.com/images/I/41nndzXt2eL._SL1500_.jpg",
    "https://m.media-amazon.com/images/I/31U4rd+WCML._SL1500_.jpg",
    "https://m.media-amazon.com/images/I/31jNdwOpP+L._SL1500_.jpg",
    "https://m.media-amazon.com/images/I/314rC4yb3wL._SL1500_.jpg",
    "https://m.media-amazon.com/images/I/315MRaUGfRL._SL1500_.jpg",
    "https://m.media-amazon.com/images/I/31lCWVWorQL._SL1500_.jpg",
    "https://m.media-amazon.com/images/I/31r2gbb-GXL._SL1500_.jpg"
  ],
  "high_res_gallery": [],
  "prime_eligible": true,
  "fulfilled_by_amazon": false,
  "seller_info_text": "Havenova.",
  "sold_by_amazon": false,
  "rating": 4.6,
  "availability_text": "Only 2 left in stock.",
  "in_stock": true,
  "description": "First Steps pack of 6 sensory balls. This pack of six sensory balls is a great addition to any children's collection, made from PP material and available in six assorted colourways, ideal for helping children develop their tactile skills. Each ball has a different texture and measures approximately 5cm in diameter, the ideal size for those little hands and feet. Their bright attractive eye catching colours are perfect for young children , making them great for developing not only motion skills, but learning colours too. Six assorted colours. Orange, green, purple, yellow, blue and pink. Suitable from 6 months +",
  "specifications_table": {
    "Brand Name": "RSW",
    "Age Range Description": "Kid",
    "Sport Type": "Golf",
    "Number of Items": "6",
    "ASIN": "B09LR297CC",
    "Unit Count": "1.00 count"
  },
  "selleramp": {
    "status": "SellerAmp extraction disabled"
  },
  "keepa": {
    "status": "Extraction process completed",
    "sales_rank_details_table": {
      "main_cat_current_rank": 568894,
      "main_cat_name": "Toys & Games",
      "sub_cat_current_rank": 447,
      "sub_cat_name": "Balls for Babies & Toddlers 3"
    },
    "ai_graph_analysis_status": "Keepa Graph AI Analysis disabled",
    "product_details_tab_data": {
      "Title": "RSW Pack Of 6 Baby Sensory Balls Assorted Textures For Motor Skills & Development And Perfect Colour Teaching Learning",
      "Sales Rank - Reference": "Toys & Games",
      "Sales Rank - Display Group": "toy_display_on_website",
      "Last Price Change": "2 months ago",
      "Buy Box - Buy Box Seller": "Havenova. (91% positive over last 12 months)",
      "Buy Box - Shipping Country": "GB",
      "FBA Pick&Pack Fee": 2.65,
      "Referral Fee %": "14.99 %",
      "Referral Fee based on current Buy Box price": 1.19,
      "Total Offer Count": "3",
      "Tracking since": "2023/06/06",
      "Listed since": "2021/11/12",
      "Categories - Root": "Toys & Games",
      "Categories - Sub": "Baby Balls",
      "Categories - Tree": "Toys & Games › Baby & Toddler Toys › Baby Toys › Baby Balls",
      "Website Display Group - Name": "Sports",
      "ASIN": "B09LR297CC",
      "Product Codes - EAN": "5015302117764",
      "Type": "RECREATION_BALL",
      "Brand": "RSW",
      "Product Group": "Sports",
      "Color": "Purple",
      "Unit Details - Unit Value": "1",
      "Unit Details - Unit Type": "count",
      "Material": "Polypropylene (PP)",
      "Number of Items": "6",
      "Package - Dimension (cm³)": "24.9 x 19.9 x 6.0 cm (= 2,973 cm³ )",
      "Package - Weight (g)": "220",
      "Package - Quantity": "0"
    }
  },
  "eans_on_page": [
    "5015302117764"
  ],
  "ean_on_page_source": "Keepa_Product_Details",
  "ean_on_page": "5015302117764",
  "sales_rank": 568894,
  "category": "Toys & Games",
  "sales_rank_source": "Keepa_SalesRankDetailsTable",
  "estimated_monthly_sales_from_bsr": 7,
  "asin_extracted_from_page": "B09LR297CC",
  "asin_queried": "B09LR297CC",
  "asin": "B09LR297CC",
  "_search_method_used": "EAN"
}