{
  "asin_from_details": "B09F99B68P",
  "title": "Aquafresh Mouthwash Fresh Mint 500ml | Pack of 3",
  "current_price": 9.45,
  "original_price": 9.99,
  "main_image": "https://m.media-amazon.com/images/I/61DN49iE92L._AC_SL1500_.jpg",
  "thumbnails": [
    "https://m.media-amazon.com/images/I/41dz3TAkQpL._AC_SR38,50_.jpg",
    "https://m.media-amazon.com/images/I/416SW-NKK0L._AC_SR38,50_.jpg",
    "https://m.media-amazon.com/images/I/513YNbYQXQL._AC_SR38,50_.jpg",
    "https://m.media-amazon.com/images/I/51vtU4DDpSL._AC_SR38,50_.jpg",
    "https://m.media-amazon.com/images/I/51U-YGoOf3L._AC_SR38,50_.jpg"
  ],
  "high_res_gallery": [],
  "prime_eligible": false,
  "fulfilled_by_amazon": false,
  "seller_info_text": "PSM discounts",
  "sold_by_amazon": false,
  "rating": 4.5,
  "review_count": 30,
  "availability_text": "In stock",
  "in_stock": true,
  "description": "Directions Add 15ml (3 x 5ml teaspoonfuls) to half a glass of water and rinse thoroughly for 30 seconds - do not swallow - spit out. Safety Warning Do not swallow. Keep out of reach of children. If swallowed, seek medical advice immediately.",
  "selleramp": {
    "status": "SellerAmp extraction disabled"
  },
  "keepa": {
    "status": "Extraction process completed",
    "sales_rank_details_table": {
      "main_cat_current_rank": 43698,
      "main_cat_name": "Health & Personal Care 13 drops / month",
      "sub_cat_current_rank": 0,
      "sub_cat_name": "-1 0"
    },
    "ai_graph_analysis_status": "Keepa Graph AI Analysis disabled",
    "product_details_tab_data": {
      "Title": "Aquafresh Mouthwash Fresh Mint 500ml | Pack of 3",
      "Sales Rank - Reference": "Health & Personal Care",
      "Sales Rank - Display Group": "health_and_beauty_display_on_website",
      "Reviews - Rating": 4.5,
      "Reviews - Rating Count": 30.0,
      "Last Price Change": "just now",
      "Buy Box - Buy Box Seller": "PSM discounts (92% positive over last 12 months)",
      "Buy Box - Shipping Country": "GB",
      "Buy Box - Strikethrough Price": "£ 9.99",
      "Lowest FBA Seller": "AFTA (100% positive over last 12 months)",
      "FBA Pick&Pack Fee": 3.34,
      "Referral Fee %": "15.02 %",
      "Referral Fee based on current Buy Box price": 1.42,
      "Lowest FBM Seller": "PSM discounts (92% positive over last 12 months) myShop UK (93% positive over last 12 months)",
      "Total Offer Count": "3",
      "Tracking since": "2021/09/02",
      "Listed since": "2021/09/02",
      "Categories - Root": "Health & Personal Care",
      "Categories - Sub": "Mouthwashes",
      "Categories - Tree": "Health & Personal Care › Dental Care › Mouthwashes",
      "Website Display Group - Name": "Grocery",
      "ASIN": "B09F99B68P",
      "Product Codes - EAN": "5060777854201",
      "Product Codes - PartNumber": "295451",
      "Freq. Bought Together": "B09XYDLY3H",
      "Type": "MOUTHWASH",
      "Brand": "multiple",
      "Product Group": "Grocery",
      "Size": "500 ml (Pack of 3)",
      "Unit Details - Unit Value": "1500",
      "Unit Details - Unit Type": "millilitre",
      "Item Form": "Liquid",
      "Product Benefit": "Aquafresh",
      "Number of Items": "3",
      "Package - Dimension (cm³)": "25.7 x 22.8 x 7.9 cm (= 4,629 cm³ )",
      "Package - Weight (g)": "1,670",
      "Active Ingredients": "mint",
      "Safety Warning": "Do not swallow. Keep out of reach of children. If swallowed, seek medical advice immediately."
    }
  },
  "eans_on_page": [
    "5060777854201"
  ],
  "ean_on_page_source": "Keepa_Product_Details",
  "ean_on_page": "5060777854201",
  "sales_rank": 43698,
  "category": "Health & Personal Care 13",
  "sales_rank_source": "Keepa_SalesRankDetailsTable",
  "estimated_monthly_sales_from_bsr": 20,
  "asin_extracted_from_page": "B09F99B68P",
  "asin_queried": "B09F99B68P",
  "asin": "B09F99B68P",
  "_search_method_used": "title"
}