{
  "asin_from_details": "B0CHWL26T1",
  "title": "The Most Incredible Exploration Stories Ever Told: A Collection of Extraordinary Tales From Our World's Greatest Explorers",
  "original_price": 25.0,
  "main_image": "https://m.media-amazon.com/images/I/812aoVfbijL._SL1500_.jpg",
  "thumbnails": [],
  "high_res_gallery": [],
  "amazon_product_details_section": {
    "ASIN\n                                            ‏\n                                            :\n                                            ‎": "B0CHWL26T1",
    "Accessibility\n                                            ‏\n                                            :\n                                            ‎": "Learn more",
    "Publication date\n                                            ‏\n                                            :\n                                            ‎": "11 Sept. 2023",
    "Language\n                                            ‏\n                                            :\n                                            ‎": "English",
    "File size\n                                            ‏\n                                            :\n                                            ‎": "2.7 MB",
    "Enhanced typesetting\n                                            ‏\n                                            :\n                                            ‎": "Enabled",
    "X-Ray\n                                            ‏\n                                            :\n                                            ‎": "Not Enabled",
    "Word Wise\n                                            ‏\n                                            :\n                                            ‎": "Enabled",
    "Print length\n                                            ‏\n                                            :\n                                            ‎": "115 pages",
    "Page Flip\n                                            ‏\n                                            :\n                                            ‎": "Enabled",
    "Customer reviews": "4.1 4.1 out of 5 stars (94) var dpAcrHasRegisteredArcLinkClickAction; P.when('A', 'ready').execute(function(A) { if (dpAcrHasRegisteredArcLinkClickAction !== true) { dpAcrHasRegisteredArcLinkClickAction = true; A.declarative( 'acrLink-click-metrics', 'click', { \"allowLinkDefault\": true }, function (event) { if (window.ue) { ue.count(\"acrLinkClickCount\", (ue.count(\"acrLinkClickCount\") || 0) + 1); } } ); } }); P.when('A', 'cf').execute(function(A) { A.declarative('acrStarsLink-click-metrics', 'click', { \"allowLinkDefault\" : true }, function(event){ if(window.ue) { ue.count(\"acrStarsLinkWithPopoverClickCount\", (ue.count(\"acrStarsLinkWithPopoverClickCount\") || 0) + 1); } }); });",
    "ASIN\n                                            ‏": "‎ B0CHWL26T1",
    "Accessibility\n                                            ‏": "‎ Learn more",
    "Publication date\n                                            ‏": "‎ 11 Sept. 2023",
    "Language\n                                            ‏": "‎ English",
    "File size\n                                            ‏": "‎ 2.7 MB",
    "Enhanced typesetting\n                                            ‏": "‎ Enabled",
    "X-Ray\n                                            ‏": "‎ Not Enabled",
    "Word Wise\n                                            ‏": "‎ Enabled",
    "Print length\n                                            ‏": "‎ 115 pages",
    "Page Flip\n                                            ‏": "‎ Enabled",
    "Best Sellers Rank": "123,910 in Kindle Store (See Top 100 in Kindle Store) 27 in History of Discovery & Exploration 38 in History of Arctic & Antarctic 168 in Adventurer & Explorer Biographies"
  },
  "prime_eligible": false,
  "fulfilled_by_amazon": false,
  "rating": 4.1,
  "review_count": 94,
  "description": "Explore the Uncharted with The Most Incredible Exploration Stories Ever Told ! Embark on an unforgettable journey through time and across the globe with this captivating collection of exploration stories that will ignite your sense of adventure and curiosity. In The Most Incredible Exploration Stories Ever Told , we invite you to dive headfirst into the thrilling tales of intrepid explorers who dared to venture into the unknown, unveiling the mysteries of our world. Among several others, you’ll learn about the exploits and adventures of: Marco Polo, the Venetian explorer who became an emissary of Kublai Khan and helped forge a connection between East and West. Christopher Columbus, the immortally world-renowned man of mysterious origins who was famous for being the first European to cross the Atlantic and discover America…or was he? James Cook, the British maritime cartographer who circumnavigated Antarctica, mapped Australia and New Zealand, discovered the Bering Strait, and discovered numerous islands throughout the Pacific, including Hawaii, where he met a gruesome end. David Livingstone, the abolitionist who embarked on a four-year journey throughout Africa in an obsessive quest to discover the source of the Nile River. In the process, he discovered Victoria Falls, crossed the width of southern Africa, and helped bring an end to the Arab-Swahili slave trade. Ernest Shackleton, a legendary Antarctic explorer, led the ill-fated Endurance expedition in 1914. Despite their ship's crushing by ice, Shackleton's exceptional leadership and determination saved his crew from disaster. His remarkable resilience and commitment to their survival during a harrowing journey across the ice make him an icon of Antarctic exploration. Whether you're an armchair explorer or a seasoned globetrotter, The Most Incredible Exploration Stories Ever Told is your passport to the greatest journeys ever undertaken. Join us on a quest to satiate your wanderlust and ignite your passion for the unknown. Read more",
  "selleramp": {
    "status": "SellerAmp extraction disabled"
  },
  "keepa": {
    "status": "Extraction process completed",
    "sales_rank_details_table": {
      "main_cat_current_rank": 123910,
      "main_cat_name": "Kindle Store 1.3 drops / month",
      "sub_cat_current_rank": 38,
      "sub_cat_name": "History of Arctic & Antarctic 3"
    },
    "ai_graph_analysis_status": "Keepa Graph AI Analysis disabled",
    "product_details_tab_data": {
      "Title": "The Most Incredible Exploration Stories Ever Told: A Collection of Extraordinary Tales From Our World's Greatest Explorers",
      "Sales Rank - Reference": "Kindle Store",
      "Sales Rank - Display Group": "ebooks_display_on_website",
      "Reviews - Rating": 4.1,
      "Reviews - Rating Count": 94.0,
      "Last Price Change": "19 months ago",
      "Buy Box - Buy Box Seller": "Amazon",
      "Buy Box - Shipping Country": "GB",
      "Total Offer Count": "1",
      "Tracking since": "2023/09/15",
      "Categories - Root": "Kindle Store",
      "Categories - Sub": "Biography & True Accounts / Arctic & Antarctica / Discovery & Exploration / World / Adventurers & Explorers",
      "Categories - Tree": "Kindle Store › Kindle eBooks › Biography & True Accounts",
      "Website Display Group - Name": "eBooks",
      "ASIN": "B0CHWL26T1",
      "Type": "ABIS_EBOOKS",
      "Product Group": "Digital Ebook Purchas",
      "Format": "Kindle eBook",
      "Author": "Hunt, Jonathan",
      "Contributors": "Hunt, Jonathan: Author",
      "Binding": "Kindle Edition",
      "Number of Pages": "115",
      "Publication Date": "2023-09-11",
      "Release Date": "2023-09-11",
      "Languages": "English: Published",
      "Package - Quantity": "0"
    }
  },
  "sales_rank": 123910,
  "category": "Kindle Store 1.3",
  "sales_rank_source": "Keepa_SalesRankDetailsTable",
  "estimated_monthly_sales_from_bsr": 2,
  "asin_extracted_from_page": "B0CHWL26T1",
  "asin_queried": "B0CHWL26T1",
  "asin": "B0CHWL26T1",
  "_search_method_used": "EAN"
}