{
  "asin_from_details": "B0056HGL14",
  "title": "Unique Party 59011 - White Paper Party Bags, Pack of 12",
  "current_price": 2.49,
  "original_price": 3.49,
  "amazon_monthly_sales_badge": 50,
  "main_image": "https://m.media-amazon.com/images/I/41uPS4j3bFL._AC_SL1000_.jpg",
  "thumbnails": [
    "https://m.media-amazon.com/images/I/31zwEt49SCL._SL1500_.jpg",
    "https://m.media-amazon.com/images/I/41E-yPesCXL._SL1500_.jpg",
    "https://m.media-amazon.com/images/I/31xMSEKgkaL._SL1500_.jpg",
    "https://m.media-amazon.com/images/I/41gc-IG3SCL._SL1500_.jpg",
    "https://m.media-amazon.com/images/I/31W6W-OkWsL._SL1500_.jpg"
  ],
  "high_res_gallery": [],
  "amazon_product_details_section": {
    "Date First Available": "7 April 2010"
  },
  "date_first_available_from_details": "7 April 2010",
  "prime_eligible": false,
  "fulfilled_by_amazon": false,
  "rating": 4.3,
  "review_count": 1828,
  "availability_text": "In stock",
  "in_stock": true,
  "features": [
    "Pack of 12 White Paper Party Bags",
    "White Paper Favour Bags measure approximately 25cm x 13cm x 9cm (10\" x 5\" x 3.5\")",
    "Ideal for handing out treats at a wedding, baby shower, bridal shower, birthday party or Christening",
    "Fill with sweets, cake or party favours to thank guests for attending your celebration",
    "Coordinate with other white party supplies and party decorations from Unique Party"
  ],
  "description": "From the manufacturer Black Tissue Paper Sheets, Pack of 10 Black Polka Dot Party Bags, Pack of 8 Cellophane Black Party Bags, Pack of 30 Cellophane Black Striped Party Bags, Pack of 20 Cellophane Black Polka Dot Party Bags, Pack of 20 Black Paper Party Bags, Pack of 12 Buying Options Buying Options Buying Options Buying Options Buying Options Add To Basket Customer Reviews 4.5 out of 5 stars 389 4.2 out of 5 stars 16 4.3 out of 5 stars 111 4.3 out of 5 stars 60 4.3 out of 5 stars 1,107 4.3 out of 5 stars 1,828 Price — no data — no data — no data — no data — no data £3.39 £ 3 . 39 Click to view additional party gift bags &amp; packaging accessories Wrap your gifts in classic bold colour with these Black Tissue Paper Sheets. Send your party guests home in style with these Black Polka Dot Favour Bags! Your guests are in for a treat with these Cellophane Black Party Bags. Create eye-catching party favours to thank guests for attending with these Cellophane Black Striped Party Bags. Create eye-catching party favours to thank guests for attending with these Cellophane Black Polka Dot Party Bags. Your guests are in for a treat with these Black Paper Party Bags. More colour options available More colour options available More colour options available More colour options available More colour options available More colour options available 90m Black Curling Ribbon 450m Black Curling Ribbon Black Polka Dot Popcorn Treat Boxes, Pack of 8 Medium Black Polka Dot Gift Bag Midnight Black Stripes Medium Gift Bag Black Striped Wine Bag Buying Options Buying Options Buying Options Buying Options Buying Options Buying Options Customer Reviews 4.5 out of 5 stars 4,981 4.5 out of 5 stars 4,981 4.0 out of 5 stars 138 3.8 out of 5 stars 71 — — Price — no data — no data — no data — no data — no data — no data Click to view additional party gift bags &amp; packaging accessories This Black Curling Ribbon gives an extra touch of style to any gift package. Add some extra decorative flair to the party scene with this Black Curling Ribbon. Hand out sweets and treats in style with these Black Polka Dot Treat Boxes. Wrap gifts for any occasion with this stylish Medium Black Polka Dot Gift Bag. Wrap gifts for any occasion with this Medium Black Striped Gift Bag. Package your present in classic elegance with this Black Striped Wine Bag. More colour options available More colour options available More colour options available More colour options available More colour options available More colour options available",
  "specifications_table": {
    "Product Dimensions": "‎25.4 x 13.34 x 8.89 cm; 110 g",
    "Manufacturer recommended age": "‎36 months - 18 years",
    "Item model number": "‎59011",
    "Number of pieces": "‎1",
    "Assembly Required": "‎No",
    "Batteries Required?": "‎No",
    "Batteries included?": "‎No",
    "Material Type(s)": "‎Paper",
    "Remote Control Included?": "‎No",
    "Colour": "‎White",
    "Release date": "‎24 Nov. 2020",
    "ASIN": "‎B0056HGL14"
  },
  "selleramp": {
    "status": "SellerAmp extraction disabled"
  },
  "keepa": {
    "status": "Extraction process completed",
    "ai_graph_analysis_status": "Keepa Graph AI Analysis disabled"
  },
  "asin_extracted_from_page": "B0056HGL14",
  "asin_queried": "B0056HGL14",
  "asin": "B0056HGL14",
  "_search_method_used": "EAN"
}