{
  "asin_from_details": "B0D7ZX4RCF",
  "title": "MOKANI Hot Water Bottle Belt, 1L Wearable Wrap Around Hot Water Bottle Set with Cover, Long Rubber Hot Water Bag for Shoulder, Neck, Waist, Back, Foot and Period Relief for Women (Animal)",
  "current_price": 7.64,
  "original_price": 37.99,
  "amazon_monthly_sales_badge": 400,
  "main_image": "https://m.media-amazon.com/images/I/71hId6nzKEL._AC_SL1500_.jpg",
  "thumbnails": [
    "https://m.media-amazon.com/images/I/41pgBRfEo-L._SL1500_.jpg",
    "https://m.media-amazon.com/images/I/41dPz-X8rsL._SL1500_.jpg",
    "https://m.media-amazon.com/images/I/41aa81UQp-L._SL1500_.jpg",
    "https://m.media-amazon.com/images/I/51dSc12w5wL._SL1500_.jpg",
    "https://m.media-amazon.com/images/I/51UgKjolJxL._SL1500_.jpg",
    "https://m.media-amazon.com/images/I/41XYXka8MGL._SL1500_.jpg",
    "https://m.media-amazon.com/images/I/41cSY+uZ2aL._SL1500_.jpg"
  ],
  "high_res_gallery": [],
  "amazon_product_details_section": {
    "Package Dimensions\n                                            ‏\n                                            :\n                                            ‎": "29.7 x 19.6 x 6.4 cm; 300 g",
    "Manufacturer\n                                            ‏\n                                            :\n                                            ‎": "Mokani",
    "ASIN\n                                            ‏\n                                            :\n                                            ‎": "B0D7ZX4RCF",
    "Item model number\n                                            ‏\n                                            :\n                                            ‎": "YD010-01",
    "Country of origin\n                                            ‏\n                                            :\n                                            ‎": "China",
    "Customer reviews": "4.6 4.6 out of 5 stars (331) var dpAcrHasRegisteredArcLinkClickAction; P.when('A', 'ready').execute(function(A) { if (dpAcrHasRegisteredArcLinkClickAction !== true) { dpAcrHasRegisteredArcLinkClickAction = true; A.declarative( 'acrLink-click-metrics', 'click', { \"allowLinkDefault\": true }, function (event) { if (window.ue) { ue.count(\"acrLinkClickCount\", (ue.count(\"acrLinkClickCount\") || 0) + 1); } } ); } }); P.when('A', 'cf').execute(function(A) { A.declarative('acrStarsLink-click-metrics', 'click', { \"allowLinkDefault\" : true }, function(event){ if(window.ue) { ue.count(\"acrStarsLinkWithPopoverClickCount\", (ue.count(\"acrStarsLinkWithPopoverClickCount\") || 0) + 1); } }); });",
    "Package Dimensions\n                                            ‏": "‎ 29.7 x 19.6 x 6.4 cm; 300 g",
    "Manufacturer\n                                            ‏": "‎ Mokani",
    "ASIN\n                                            ‏": "‎ B0D7ZX4RCF",
    "Item model number\n                                            ‏": "‎ YD010-01",
    "Country of origin\n                                            ‏": "‎ China"
  },
  "dimensions_from_details": "‎ 29.7 x 19.6 x 6.4 cm; 300 g",
  "manufacturer_from_details": "‎ Mokani",
  "prime_eligible": false,
  "fulfilled_by_amazon": false,
  "seller_info_text": "Mokani Store",
  "sold_by_amazon": false,
  "rating": 4.6,
  "review_count": 331,
  "availability_text": "In stock",
  "in_stock": true,
  "features": [
    "【Important Notes Before Purchase】1. Do not fill the hot water bottle with water exceeding 70°C to avoid scalding; 2. Before use, always check the hot water bottle for leaks. If any leaks are found, please stop using it ! 3. Do not use directly on skin; use with a flannel cover.",
    "【Safety & Lifespan of the Bottle】The hot water bottle with cover is made of high-quality natural rubber, which is sturdy and wear-resistant, with better thermal conductivity and longer insulation time. The recommended lifespan of a hot water bottle is 2 years. For safety reasons, please replace it every two years.",
    "【Wide Mouth Anti-Leakage】The mouth of the wearable hot water bottle is wide enough to easily pour water into the bottle with a capacity of 1L. The bottle is designed with a spiral nibble to seal the bottle and prevent leakage. For safety, please hold the bottle vertically by the neck and pour hot water slowly to avoid spillage. It is recommended that you do not fill the bottle more than 2/3 of the way and that the water temperature is below 70°C.",
    "【Cosy Plush Belt】The wearable hot water bottle is designed with a super soft double lining to keep your hands and waist warm at the same time. The belt is 118cm in length and is self-adjusting to fit all body shapes. The included plush pouch helps to retain heat inside the wrap around hot water bottle and also prevents burns from direct heat contact with the skin.",
    "【Multifunctional Hot Water Bottle】It helps to relieve lower back pain, back pain, neck pain, shoulder pain, muscle aches and pains, menstrual cramps, tension, or sports injuries. Suitable for both adults and girls. You can also use the hot water bag filled with cold water or crushed ice to provide a hot compress for a child with a fever or to reduce swelling in a sprained ankle.",
    "【Ideal Gift】Wrap around hot water bottle is one of the essential thermal products for homes, school, office, and other places. The hot water bottle gift set is an ideal Mother's Day, Valentine's Day, Christmas, Birthday, or New Year gift for your wife, girlfriend, friends, and colleagues."
  ],
  "description": "Product Description To avoid water leakage and scalding, please read the instructions carefully. Heartwarming Designs Wide mouth design Easy to fill while preventing spills. Note：Before use, please tighten the cap, if there are leaks, do not use! Soft plush lining Prevents burns from direct contact with your skin With hand pockets Warms your waist and your hands at the same time High-quality rubber material Hot and cold for all seasons, suitable for office, home, school, and other places. Note：Water below 70 \"C. Previous page Next page 1 Instructions Safety Guide 2 Important Safety Warnings 3 Burn Risks &amp; Warnings 4 Troubleshooting 5 Disclaimer Essential for keeping warm in winter Hooded Towel Poncho Add To Basket Hot Water Bottle Belt Buying Options Blanket Hoodie Kids Add To Basket Blanket Hoodie Kids Add To Basket Winter Cycling Gloves Buying Options Christmas Bags Buying Options Kids Hooded Poncho Towel Add To Basket Customer Reviews 4.6 out of 5 stars 331 4.5 out of 5 stars 595 4.5 out of 5 stars 418 4.5 out of 5 stars 30 4.3 out of 5 stars 815 4.6 out of 5 stars 1,098 4.4 out of 5 stars 252 Price £7.99 £ 7 . 99 £7.25 £ 7 . 25 £11.99 £ 11 . 99 £6.79 £ 6 . 79 £8.99 £ 8 . 99 — £9.99 £ 9 . 99 Styles Husky Samoyed Sky Green Black 16 Designs Blue Unicorn Size 118 cm 120 cm 66W x 75L cm 66W x 70L cm Black 4 Patterns 60L x 60W cm Applicable population Women &amp; Men &amp; Elderly Women &amp; Men &amp; Elderly Girls &amp; Boys Girls &amp; Boys Women &amp; Men Girls &amp; Boys Girls &amp; Boys Occasions for use Indoor &amp; Outdoor &amp; Office Indoor &amp; Outdoor &amp; Office Indoor &amp; outdoor &amp; school Indoor &amp; outdoor &amp; school Indoor &amp; Outdoor &amp; Office Christmas Party Bathing &amp; Beach &amp; Swimming Keep Warm ✔ ✔ ✔ ✔ ✔ ✘ ✔",
  "specifications_table": {
    "Brand Name": "MOKANI",
    "Age Range Description": "Adult",
    "Number of Items": "1",
    "Model Name": "YD010",
    "Manufacturer": "Mokani",
    "Customer Reviews": "4.6 4.6 out of 5 stars (331) var dpAcrHasRegisteredArcLinkClickAction; P.when('A', 'ready').execute(function(A) { if (dpAcrHasRegisteredArcLinkClickAction !== true) { dpAcrHasRegisteredArcLinkClickAction = true; A.declarative( 'acrLink-click-metrics', 'click', { \"allowLinkDefault\": true }, function (event) { if (window.ue) { ue.count(\"acrLinkClickCount\", (ue.count(\"acrLinkClickCount\") || 0) + 1); } } ); } }); P.when('A', 'cf').execute(function(A) { A.declarative('acrStarsLink-click-metrics', 'click', { \"allowLinkDefault\" : true }, function(event){ if(window.ue) { ue.count(\"acrStarsLinkWithPopoverClickCount\", (ue.count(\"acrStarsLinkWithPopoverClickCount\") || 0) + 1); } }); }); 4.6 out of 5 stars",
    "ASIN": "B0D7ZX4RCF",
    "Country Of Origin": "China"
  },
  "selleramp": {
    "status": "SellerAmp extraction disabled"
  },
  "keepa": {
    "status": "Extraction process completed",
    "ai_graph_analysis_status": "Keepa Graph AI Analysis disabled"
  },
  "asin_extracted_from_page": "B0D7ZX4RCF",
  "asin_queried": "B0D7ZX4RCF",
  "asin": "B0D7ZX4RCF",
  "_search_method_used": "title"
}