{
  "asin_from_details": "B0F9PFHHXW",
  "title": "Clutch Tote Handbags, Small Black Handbag, Mini Hobo Bag Shoulder Purse for Women, Mini Handbags with Zipper Closure, PU Leather Shoulder Bags Vintage for Shopping Dating Daily Use",
  "current_price": 8.99,
  "original_price": 32.99,
  "main_image": "https://m.media-amazon.com/images/I/51wP94HrVCL._AC_SL1500_.jpg",
  "thumbnails": [
    "https://m.media-amazon.com/images/I/31Cw5hSWGpL._SL1500_.jpg",
    "https://m.media-amazon.com/images/I/417BRBF21vL._SL1500_.jpg",
    "https://m.media-amazon.com/images/I/41DArHoCIxL._SL1500_.jpg",
    "https://m.media-amazon.com/images/I/41FVt6i3NcL._SL1500_.jpg",
    "https://m.media-amazon.com/images/I/41xO+1XgyfL._SL1500_.jpg",
    "https://m.media-amazon.com/images/I/41RB6x0qMxL._SL1500_.jpg",
    "https://m.media-amazon.com/images/I/41U+6SL7dFL._SL1500_.jpg"
  ],
  "high_res_gallery": [],
  "amazon_product_details_section": {
    "Product Dimensions\n                                            ‏\n                                            :\n                                            ‎": "25 x 15 x 5 cm; 210 g",
    "Date First Available\n                                            ‏\n                                            :\n                                            ‎": "23 May 2025",
    "Manufacturer\n                                            ‏\n                                            :\n                                            ‎": "Marjoramy",
    "ASIN\n                                            ‏\n                                            :\n                                            ‎": "B0F9PFHHXW",
    "Item model number\n                                            ‏\n                                            :\n                                            ‎": "301-72773",
    "Country of origin\n                                            ‏\n                                            :\n                                            ‎": "China",
    "Department\n                                            ‏\n                                            :\n                                            ‎": "Women's",
    "Customer reviews": "5.0 5.0 out of 5 stars (1) var dpAcrHasRegisteredArcLinkClickAction; P.when('A', 'ready').execute(function(A) { if (dpAcrHasRegisteredArcLinkClickAction !== true) { dpAcrHasRegisteredArcLinkClickAction = true; A.declarative( 'acrLink-click-metrics', 'click', { \"allowLinkDefault\": true }, function (event) { if (window.ue) { ue.count(\"acrLinkClickCount\", (ue.count(\"acrLinkClickCount\") || 0) + 1); } } ); } }); P.when('A', 'cf').execute(function(A) { A.declarative('acrStarsLink-click-metrics', 'click', { \"allowLinkDefault\" : true }, function(event){ if(window.ue) { ue.count(\"acrStarsLinkWithPopoverClickCount\", (ue.count(\"acrStarsLinkWithPopoverClickCount\") || 0) + 1); } }); });",
    "Product Dimensions\n                                            ‏": "‎ 25 x 15 x 5 cm; 210 g",
    "Date First Available\n                                            ‏": "‎ 23 May 2025",
    "Manufacturer\n                                            ‏": "‎ Marjoramy",
    "ASIN\n                                            ‏": "‎ B0F9PFHHXW",
    "Item model number\n                                            ‏": "‎ 301-72773",
    "Country of origin\n                                            ‏": "‎ China",
    "Department\n                                            ‏": "‎ Women's",
    "Best Sellers Rank": "2,157,576 in Fashion (See Top 100 in Fashion) 10,049 in Women's Hobos & Shoulder Bags"
  },
  "date_first_available_from_details": "‎ 23 May 2025",
  "manufacturer_from_details": "‎ Marjoramy",
  "prime_eligible": true,
  "fulfilled_by_amazon": false,
  "seller_info_text": "Marjoramy",
  "sold_by_amazon": false,
  "rating": 5.0,
  "review_count": 1,
  "availability_text": "In stock",
  "in_stock": true,
  "description": "Product information: Explore your unique style with our premium black shoulder bag, designed to be your go-to accessory for all occasions. Specifications: Material: PU Size: 25x15x5cm Colour: Black Weight: 210g Package contains: 1 x Shoulder Bag Features: 1.Crafted from high-quality PU leather, our shoulder bag promises elegance and durability, featuring a sleek design that's perfect for vegan fashionistas. 2.Expertly crafted from durable PU material, this small handbag for women is both lightweight and spacious, accommodating your daily essentials effortlessly. 3.With its classic black design, this handbag transitions seamlessly from casual day outings to sophisticated evening events, making it a must-have accessory. 4.This small handbag for women makes an excellent present for birthdays, Valentine's Day, Mother's Day, Christmas, and graduations, combining style with everyday utility. Note: 1.Due to manual measurement, the size and weight may have some error. 2.Due to the difference between monitors, there may be a slight colour difference.",
  "selleramp": {
    "status": "SellerAmp extraction disabled"
  },
  "keepa": {
    "status": "Extraction process completed",
    "ai_graph_analysis_status": "Keepa Graph AI Analysis disabled"
  },
  "asin_extracted_from_page": "B0F9PFHHXW",
  "asin_queried": "B0F9PFHHXW",
  "asin": "B0F9PFHHXW",
  "_search_method_used": "title"
}