{
  "asin_from_details": "B07K8RMFV6",
  "title": "Falcon Housewares 6cm White Enamel Espresso Mug (2)",
  "current_price": 9.95,
  "original_price": 37.69,
  "main_image": "https://m.media-amazon.com/images/I/51nb--xsnIL._AC_SL1000_.jpg",
  "thumbnails": [
    "https://m.media-amazon.com/images/I/41p1fy4905L._SL1500_.jpg"
  ],
  "high_res_gallery": [],
  "amazon_product_details_section": {
    "ASIN": "B07K8RMFV6",
    "Date First Available": "7 Nov. 2018"
  },
  "date_first_available_from_details": "7 Nov. 2018",
  "prime_eligible": false,
  "fulfilled_by_amazon": false,
  "seller_info_text": "LFH-WarehouseDeals",
  "sold_by_amazon": false,
  "rating": 5.0,
  "review_count": 2,
  "availability_text": "Only 4 left in stock.",
  "in_stock": true,
  "specifications_table": {
    "Brand": "‎Falcon",
    "Model Number": "‎B07K8RMFV6_1",
    "Colour": "‎White",
    "Diameter": "‎6 Centimetres",
    "Material": "‎Enamel",
    "Auto Shutoff": "‎No",
    "Item Weight": "‎20 g"
  },
  "selleramp": {
    "status": "SellerAmp extraction disabled"
  },
  "keepa": {
    "status": "Extraction process completed",
    "ai_graph_analysis_status": "Keepa Graph AI Analysis disabled"
  },
  "asin_extracted_from_page": "B07K8RMFV6",
  "asin_queried": "B07K8RMFV6",
  "asin": "B07K8RMFV6",
  "_search_method_used": "EAN"
}