{
  "asin_from_details": "B0BHSJH7ZC",
  "title": "maikun Black Leather Belts for Men,Mens Belts Leather Black",
  "current_price": 9.99,
  "main_image": "https://m.media-amazon.com/images/I/71tIu0B04wL._AC_SL1500_.jpg",
  "thumbnails": [
    "https://m.media-amazon.com/images/I/41FX4Of3cgL._AC_SR38,50_.jpg",
    "https://m.media-amazon.com/images/I/41yjnLxCO7L._AC_SR38,50_.jpg",
    "https://m.media-amazon.com/images/I/41UXd-fhJeL._AC_SR38,50_.jpg",
    "https://m.media-amazon.com/images/I/41DSxuZys+L._AC_SR38,50_.jpg",
    "https://m.media-amazon.com/images/I/61Kxg7abjGL._AC_SR38,50_.jpg",
    "https://m.media-amazon.com/images/I/51fw18Os8XL._AC_SR38,50_.jpg",
    "https://m.media-amazon.com/images/I/919zgDPQ8pL.SX38_SY50_CR,0,0,38,50_PKmb-play-button-overlay-thumb_.jpg"
  ],
  "high_res_gallery": [],
  "amazon_product_details_section": {
    "Date First Available\n                                            ‏\n                                            :\n                                            ‎": "25 July 2022",
    "Manufacturer\n                                            ‏\n                                            :\n                                            ‎": "maikun",
    "ASIN\n                                            ‏\n                                            :\n                                            ‎": "B0C3QWHSWJ",
    "Customer reviews": "4.3 4.3 out of 5 stars (4,722) var dpAcrHasRegisteredArcLinkClickAction; P.when('A', 'ready').execute(function(A) { if (dpAcrHasRegisteredArcLinkClickAction !== true) { dpAcrHasRegisteredArcLinkClickAction = true; A.declarative( 'acrLink-click-metrics', 'click', { \"allowLinkDefault\": true }, function (event) { if (window.ue) { ue.count(\"acrLinkClickCount\", (ue.count(\"acrLinkClickCount\") || 0) + 1); } } ); } }); P.when('A', 'cf').execute(function(A) { A.declarative('acrStarsLink-click-metrics', 'click', { \"allowLinkDefault\" : true }, function(event){ if(window.ue) { ue.count(\"acrStarsLinkWithPopoverClickCount\", (ue.count(\"acrStarsLinkWithPopoverClickCount\") || 0) + 1); } }); });",
    "Date First Available\n                                            ‏": "‎ 25 July 2022",
    "Manufacturer\n                                            ‏": "‎ maikun",
    "ASIN\n                                            ‏": "‎ B0C3QWHSWJ",
    "Best Sellers Rank": "87 in Fashion (See Top 100 in Fashion) 1 in Men's Belts"
  },
  "date_first_available_from_details": "‎ 25 July 2022",
  "manufacturer_from_details": "‎ maikun",
  "prime_eligible": true,
  "fulfilled_by_amazon": false,
  "seller_info_text": "MaiKun Brand Store",
  "sold_by_amazon": false,
  "rating": 4.3,
  "review_count": 4722,
  "availability_text": "In stock",
  "in_stock": true,
  "description": "Product Description This casual belt is an ideal men's accessory for daily wearing, complementing uniforms, jeans, formal attire, and everyday clothing for formal or informal occasions. EVERYDAY DRESS BELT This mens belt is suitable for daily wear, it's multiple used for work and outdoor activities, can be matched with work suits and casual wear. It measures 35mm in width, making it the perfect size for dressing up or dressing down. The metal buckle completes the look, adding a touch of sophistication and style to every outfit. Previous page With its impeccable craftsmanship and attention to detail, this belt is both durable and stylish. Next page 1 ELEGANT LOOK 2 HIGH QUALITY LEATHER 3 CUT TO FIT 4 GIFT CHOICE 5 ONE FOR ALL Other Choices Men Casual Belt Add To Basket Ratchet Belt Add To Basket Reversible Belt Add To Basket Vintage Belt Add To Basket Casual Belt Add To Basket Elastic belt Add To Basket Woven Elastic Belt Add To Basket Customer Reviews 4.3 out of 5 stars 4,722 4.1 out of 5 stars 212 4.3 out of 5 stars 886 4.5 out of 5 stars 1,016 4.1 out of 5 stars 1,403 4.2 out of 5 stars 73 4.5 out of 5 stars 14,235 Price £9.99 £ 9 . 99 £11.99 £ 11 . 99 £9.99 £ 9 . 99 £11.99 £ 11 . 99 £9.99 £ 9 . 99 £7.99 £ 7 . 99 £9.99 £ 9 . 99 Width 1.38\" 1.38'' 1.38'' 1.5\" 1.38'' 1.38'' 1.38'' Size Range 28-44'' 31-43\" 30-42\" 30-49\" 29-44\" 29.5-49.5\" Below 45\" Features Casual Ratchet Buckle Reversible buckle Vintage Buckle Black Buckle Metal-free buckle Elastic Belt Limitless Adjustments No No NO No No Yes Yes Trim to Fit Yes Yes Yes Yes Yes Yes NO",
  "selleramp": {
    "status": "SellerAmp extraction disabled"
  },
  "keepa": {
    "status": "Extraction process completed",
    "sales_rank_details_table": {
      "main_cat_current_rank": 87,
      "main_cat_name": "Fashion 35 drops / month",
      "sub_cat_current_rank": 1,
      "sub_cat_name": "Men's Belts 3"
    },
    "ai_graph_analysis_status": "Keepa Graph AI Analysis disabled",
    "product_details_tab_data": {
      "Title": "maikun Black Leather Belt for Men, Mens Belt for Jeans and Dresses, Black Buckle Length41inch",
      "Sales Rank - Reference": "Fashion",
      "Sales Rank - Display Group": "fashion_display_on_website",
      "Bought in past month": "1,000+",
      "Reviews - Rating": 4.3,
      "Reviews - Rating Count": 4.0,
      "Last Price Change": "13 days ago",
      "Buy Box - Buy Box Seller": "MaiKun Brand Store (98% positive over last 12 months)",
      "Lowest FBA Seller": "MaiKun Brand Store (98% positive over last 12 months)",
      "FBA Pick&Pack Fee": 2.61,
      "Referral Fee %": "5.01 %",
      "Referral Fee based on current Buy Box price": 0.5,
      "Total Offer Count": "1",
      "Tracking since": "2022/10/22",
      "Listed since": "2022/07/25",
      "Categories - Root": "Fashion",
      "Categories - Sub": "Belts",
      "Categories - Tree": "Fashion › Men › Accessories › Belts",
      "Website Display Group - Name": "Apparel",
      "ASIN": "B0BHSJH7ZC",
      "Product Codes - PartNumber": "Debelt17389-black-black-105-FBA",
      "Parent ASIN": "B0C3QWHSWJ",
      "Variation ASINs": "B0BN56HKY6, B0BHSJH7ZC, B0FCYC3FQH, B0BHSKFWMH, B0FCY8NP7D, B0B7HVP8FQ, B0BHSM4W5X, B0FCYBYGG1, B0B7HVG3SZ, B0FH23RKN5, B0FCYC8SMB, B0B7HW9DN1, ... (more than 12 ASINs, export or copy cell to get all)",
      "Freq. Bought Together": "B0DC3CK7R7, B08TQS471R",
      "Type": "APPAREL_BELT",
      "Manufacturer": "maikun",
      "Brand": "maikun",
      "Product Group": "Apparel",
      "Model": "belt17389-black-black-105-FBA",
      "Color": "Black",
      "Size": "fits waist 32-35\",Length41\"",
      "Pattern": "Solid",
      "Material": "Leather",
      "Number of Items": "1",
      "Videos - Video Count": "1",
      "Videos - Main Videos": "Creator: Main, https://m.media-amazon.com/images/I/919zgDPQ8pL.jpg, https://m.media-amazon.com/images/S/vse-vms-transcoding-artifact-eu-west-1-prod/18eb8010-ef28-4088-93fb-3872bab847a1/default.jobtemplate.hls.m3u8",
      "Package - Dimension (cm³)": "17.0 x 12.8 x 5.0 cm (= 1,088 cm³ )",
      "Package - Weight (g)": "190",
      "Package - Quantity": "1",
      "Item - Weight (g)": "180"
    }
  },
  "sales_rank": 87,
  "category": "Fashion 35",
  "sales_rank_source": "Keepa_SalesRankDetailsTable",
  "estimated_monthly_sales_from_bsr": 1000,
  "asin_extracted_from_page": "B0BHSJH7ZC",
  "asin_queried": "B0BHSJH7ZC",
  "asin": "B0BHSJH7ZC",
  "_search_method_used": "title"
}