{
  "asin_from_details": "B0C8HDGMRH",
  "title": "Mermaid Tail Hair Sparkling Pin Aurora Sequins Fish Tail Hairpin Crocodile Clips Hair Clip Starfish Shell Mermaid Design Hair Clips Accessories for Women and Girls-6 pcs",
  "current_price": 5.99,
  "main_image": "https://m.media-amazon.com/images/I/61BOFGjaZDL._AC_SL1200_.jpg",
  "thumbnails": [
    "https://m.media-amazon.com/images/I/51wpXZ6bY4L._SL1500_.jpg",
    "https://m.media-amazon.com/images/I/51Y2YOTTLzL._SL1500_.jpg",
    "https://m.media-amazon.com/images/I/51b5xhPLf1L._SL1500_.jpg",
    "https://m.media-amazon.com/images/I/41k2qCiEyKL._SL1500_.jpg",
    "https://m.media-amazon.com/images/I/51W2ZCev98L._SL1500_.jpg",
    "https://m.media-amazon.com/images/I/51RqhIL792L._SL1500_.jpg",
    "https://m.media-amazon.com/images/I/51SCbcSSPaL._SL1500_.jpg"
  ],
  "high_res_gallery": [],
  "amazon_product_details_section": {
    "Package Dimensions\n                                            ‏\n                                            :\n                                            ‎": "15 x 10.7 x 5.1 cm; 40 g",
    "Manufacturer\n                                            ‏\n                                            :\n                                            ‎": "Ainvhh",
    "ASIN\n                                            ‏\n                                            :\n                                            ‎": "B0C8HDGMRH",
    "Country of origin\n                                            ‏\n                                            :\n                                            ‎": "China",
    "Customer reviews": "4.6 4.6 out of 5 stars (57) var dpAcrHasRegisteredArcLinkClickAction; P.when('A', 'ready').execute(function(A) { if (dpAcrHasRegisteredArcLinkClickAction !== true) { dpAcrHasRegisteredArcLinkClickAction = true; A.declarative( 'acrLink-click-metrics', 'click', { \"allowLinkDefault\": true }, function (event) { if (window.ue) { ue.count(\"acrLinkClickCount\", (ue.count(\"acrLinkClickCount\") || 0) + 1); } } ); } }); P.when('A', 'cf').execute(function(A) { A.declarative('acrStarsLink-click-metrics', 'click', { \"allowLinkDefault\" : true }, function(event){ if(window.ue) { ue.count(\"acrStarsLinkWithPopoverClickCount\", (ue.count(\"acrStarsLinkWithPopoverClickCount\") || 0) + 1); } }); });",
    "Package Dimensions\n                                            ‏": "‎ 15 x 10.7 x 5.1 cm; 40 g",
    "Manufacturer\n                                            ‏": "‎ Ainvhh",
    "ASIN\n                                            ‏": "‎ B0C8HDGMRH",
    "Country of origin\n                                            ‏": "‎ China"
  },
  "dimensions_from_details": "‎ 15 x 10.7 x 5.1 cm; 40 g",
  "manufacturer_from_details": "‎ Ainvhh",
  "prime_eligible": false,
  "fulfilled_by_amazon": false,
  "seller_info_text": "Yelos US",
  "sold_by_amazon": false,
  "rating": 4.6,
  "review_count": 57,
  "availability_text": "In stock",
  "in_stock": true,
  "features": [
    "【Package Included】You will receive 6 Pcs Mermaid Hair Clips, coming in 3 different colour ( bluish violet, white, blue ) to match your changing hairstyles & clothing in different occasions.",
    "【Material】Mermaid hairclip made of high quality sequins, fabric and metal alloy. Silvery metal clip, strong, can be used for a long time.",
    "【Exquisite Design】The Hair Clips are based on the mermaid's tail. The shells, starfish and sequins make the hairpin look more lovely and delicate. Wearing them will make you more charming in the crowd.",
    "【Easy Use】These Mermaid hair clips are suitable for a variety of hairstyles, such as straight hair, curly hair, ponytails, short hair, braids, etc. You can use one or more at a time, depending on your needs.",
    "【Wide Application】 Hair Clip can be applied to many situations, and let you be the brightest one in various occasions. Such as dancing, birthdays, parties, holidays, Little Girls Mermaid Theme Party, etc."
  ],
  "description": "Product description Mermaid Tail Hair Sparkling Pin Aurora Sequins Fish Tail Hairpin Crocodile Clips Hair Clip Starfish Shell Mermaid Design Hair Clips Accessories for Women and Girls-6 pcs Directions Open the clip mechanism, position the hair clip on the desired hairstyle, and secure it in place. The hair clips are suitable for various hairstyles including straight, curly, ponytails, short hair, and braids.",
  "specifications_table": {
    "Colour": "Aurora",
    "Product Style": "Fantasy",
    "Theme": "Fantasy",
    "Occasion": "All Occasions",
    "Pattern": "Variety Pack",
    "Item Shape": "Crocodile",
    "Subject Character": "Mermaid"
  },
  "selleramp": {
    "status": "SellerAmp extraction disabled"
  },
  "keepa": {
    "status": "Extraction process completed",
    "sales_rank_details_table": {
      "main_cat_current_rank": 124444,
      "main_cat_name": "Beauty 2.7 drops / month",
      "sub_cat_current_rank": 880,
      "sub_cat_name": "Hair Pins 3"
    },
    "ai_graph_analysis_status": "Keepa Graph AI Analysis disabled",
    "product_details_tab_data": {
      "Title": "Mermaid Tail Hair Sparkling Pin Aurora Sequins Fish Tail Hairpin Crocodile Clips Hair Clip Starfish Shell Mermaid Design Hair Clips Accessories for Women and Girls-6 pcs",
      "Sales Rank - Reference": "Beauty",
      "Sales Rank - Display Group": "beauty_display_on_website",
      "Reviews - Rating": 4.6,
      "Reviews - Rating Count": 57.0,
      "Last Price Change": "5 months ago",
      "Buy Box - Buy Box Seller": "Yelos US (100% positive over last 12 months)",
      "Lowest FBA Seller": "Yelos US (100% positive over last 12 months)",
      "FBA Pick&Pack Fee": 2.65,
      "Referral Fee %": "8.01 %",
      "Referral Fee based on current Buy Box price": 0.48,
      "Total Offer Count": "1",
      "Tracking since": "2024/01/19",
      "Listed since": "2023/06/30",
      "Categories - Root": "Beauty",
      "Categories - Sub": "Hair Pins",
      "Categories - Tree": "Beauty › Hair Care › Hair Styling Accessories › Hair Pins",
      "Website Display Group - Name": "Beauty",
      "ASIN": "B0C8HDGMRH",
      "Freq. Bought Together": "B0CYBMRRGQ, B0CZL73DK7",
      "Type": "HAIR_CLIP",
      "Manufacturer": "Ainvhh",
      "Brand": "Ainvhh",
      "Product Group": "Beauty",
      "Color": "Aurora",
      "Size": "1 count (Pack of 6)",
      "Unit Details - Unit Value": "6",
      "Unit Details - Unit Type": "count",
      "Pattern": "Variety Pack",
      "Style": "Fantasy",
      "Material": "Metal, Fabric",
      "Recommended Uses": "Hairdressing",
      "Number of Items": "6",
      "Package - Dimension (cm³)": "15.0 x 10.7 x 5.1 cm (= 819 cm³ )",
      "Package - Weight (g)": "40",
      "Item - Weight (g)": "40"
    }
  },
  "sales_rank": 124444,
  "category": "Beauty 2.7",
  "sales_rank_source": "Keepa_SalesRankDetailsTable",
  "estimated_monthly_sales_from_bsr": 5,
  "asin_extracted_from_page": "B0C8HDGMRH",
  "asin_queried": "B0C8HDGMRH",
  "asin": "B0C8HDGMRH",
  "_search_method_used": "title"
}