{
  "asin_from_details": "B00ZVHZ98A",
  "title": "Professional Mini Jack to Phono Plugs | 1 x Male 3.5mm Jack to 2 x RCA Plugs",
  "current_price": 4.8,
  "main_image": "https://m.media-amazon.com/images/I/51psqsrUwxL._AC_SL1024_.jpg",
  "thumbnails": [
    "https://m.media-amazon.com/images/I/31zYmL4cAkL._SL1500_.jpg",
    "https://m.media-amazon.com/images/I/31GFG1Vm9gL._SL1500_.jpg",
    "https://m.media-amazon.com/images/I/41U0r8BawZL._SL1500_.jpg"
  ],
  "high_res_gallery": [],
  "amazon_product_details_section": {
    "Product Dimensions\n                                            ‏\n                                            :\n                                            ‎": "1.2 x 0.1 x 0.1 cm; 30 g",
    "Date First Available\n                                            ‏\n                                            :\n                                            ‎": "17 Jun. 2015",
    "Manufacturer\n                                            ‏\n                                            :\n                                            ‎": "Universal Markets Ltd",
    "ASIN\n                                            ‏\n                                            :\n                                            ‎": "B00ZVHZ98A",
    "Item model number\n                                            ‏\n                                            :\n                                            ‎": "112.134UK",
    "Guaranteed software updates until\n                                            ‏\n                                            :\n                                            ‎": "unknown",
    "Product Dimensions\n                                            ‏": "‎ 1.2 x 0.1 x 0.1 cm; 30 g",
    "Date First Available\n                                            ‏": "‎ 17 Jun. 2015",
    "Manufacturer\n                                            ‏": "‎ Universal Markets Ltd",
    "ASIN\n                                            ‏": "‎ B00ZVHZ98A",
    "Item model number\n                                            ‏": "‎ 112.134UK",
    "Guaranteed software updates until\n                                            ‏": "‎ unknown"
  },
  "date_first_available_from_details": "‎ 17 Jun. 2015",
  "manufacturer_from_details": "‎ Universal Markets Ltd",
  "prime_eligible": false,
  "fulfilled_by_amazon": false,
  "seller_info_text": "Netagon UK",
  "sold_by_amazon": false,
  "rating": 4.6,
  "availability_text": "In stock",
  "in_stock": true,
  "features": [
    "Precision connectors for mobile devices",
    "Supplied in retail friendly sealed bag",
    "Gold plated connectors",
    "1.5 Metre long"
  ],
  "description": "Product Description Precision 3.5mm Stereo Jack Plug to 2 x RCA Plugs Lead 3.5mm stereo jack to two RCA plugs audio lead with slimline metal body for connecting mobile phones or personal audio players to RCA line inputs. PRODUCT FEATURES: - Precision connectors for mobile devices - Supplied in retail friendly sealed bag - Gold plated connectors SPECIFICATION: - Cable : diameter 3mmØ - Conductor 2 x 10/0.1mmØ - Cable length 1.5m - Weight 200g Box Contains 1 x Professional Mini Jack to Phono Plugs",
  "selleramp": {
    "status": "SellerAmp extraction disabled"
  },
  "keepa": {
    "status": "Extraction process completed",
    "ai_graph_analysis_status": "Keepa Graph AI Analysis disabled"
  },
  "asin_extracted_from_page": "B00ZVHZ98A",
  "asin_queried": "B00ZVHZ98A",
  "asin": "B00ZVHZ98A",
  "_search_method_used": "EAN"
}