{
  "asin_queried": "B00DIB9O2I",
  "asin": "B00DIB9O2I",
  "url": "https://www.amazon.co.uk/dp/B00DIB9O2I",
  "_search_method_used": "EAN",
  "scraped_at": "2026-02-01T08:28:22Z",
  "selleramp": {
    "status": "not_run"
  },
  "keepa": {},
  "title": "MuslinZ Muslin Cloths for Baby - Baby Burp Cloths - 6 Pack Muslin Squares - Large 70x70cm - Pure Cotton - Soft, Absorbent &amp; Breathable - Multi Use Newborn Cloths - UK Brand (Blue)",
  "current_price": 13.99,
  "ean_on_page": "5055499001200",
  "eans_on_page": [
    "5055499001200"
  ]
}